appsettings2/Configuration.py
appsettings2/ConfigurationBuilder.py
appsettings2/ConfigurationException.py
appsettings2/__init__.py
appsettings2/helpers.py
appsettings2/providers/CommandLineConfigurationProvider.py
appsettings2/providers/ConfigurationProvider.py
appsettings2/providers/EnvironmentConfigurationProvider.py
appsettings2/providers/JsonConfigurationProvider.py
appsettings2/providers/TomlConfigurationProvider.py
appsettings2/providers/YamlConfigurationProvider.py
appsettings2/providers/__init__.py
appsettings2-1.2.8.dist-info/licenses/LICENSE
appsettings2-1.2.8.dist-info/METADATA
appsettings2-1.2.8.dist-info/WHEEL
appsettings2-1.2.8.dist-info/top_level.txt
appsettings2-1.2.8.dist-info/RECORD
