Metadata-Version: 2.4
Name: appsettings2
Version: 1.2.8
Summary: Unifies configuration sources into a Configuration object that can be bound to complex types, or accessed directly for configuration data.
Author-email: Shaun Wilson <mrshaunwilson@msn.com>
Project-URL: Documentation, https://appsettings2.readthedocs.io/
Project-URL: Homepage, https://github.com/wilson0x4d/appsettings2
Project-URL: Repository, https://github.com/wilson0x4d/appsettings2.git
Classifier: Intended Audience :: Developers
Classifier: License :: OSI Approved :: MIT License
Classifier: Operating System :: OS Independent
Classifier: Programming Language :: Python
Classifier: Topic :: Software Development :: Libraries
Requires-Python: >=3.11
License-File: LICENSE
Requires-Dist: pyyaml>=6.0.2
Dynamic: license-file
